{
    "version": "0.4.0",
    "architecture": {
        "64bit": {
            "url": "https://github.com/jorgemuza/docverter/releases/download/v0.4.0/docverter_0.4.0_windows_amd64.zip",
            "bin": [
                "docverter.exe"
            ],
            "hash": "b1daf8bf540d9ebe9a9119661c8ab057260f086e437b7712f70a8c0dc5602f89"
        },
        "arm64": {
            "url": "https://github.com/jorgemuza/docverter/releases/download/v0.4.0/docverter_0.4.0_windows_arm64.zip",
            "bin": [
                "docverter.exe"
            ],
            "hash": "4db50149460585fe8aff8eb04dfcaefb49f4c1dba312fa5be46c00fb9554b50d"
        }
    },
    "homepage": "https://github.com/jorgemuza/docverter",
    "license": "MIT",
    "description": "Unified document converter — Markdown to DOCX/PDF, Excalidraw to SVG/PNG"
}
